track_logging_model/__init__.py
track_logging_model/track_logging_model.py
track_logging_model-1.0.0.dist-info/licenses/LICENSE.lic
track_logging_model-1.0.0.dist-info/METADATA
track_logging_model-1.0.0.dist-info/WHEEL
track_logging_model-1.0.0.dist-info/top_level.txt
track_logging_model-1.0.0.dist-info/RECORD
