Metadata-Version: 2.4
Name: track_logging_model
Version: 1.0.0
Summary: Log parameters, metrics, and artifacts using track logging model .
Author: Radhika Menon
Author-email: Radhika.Menon@cognizant.com
Classifier: Programming Language :: Python :: 3
Classifier: License :: OSI Approved :: MIT License
Classifier: Operating System :: OS Independent
Requires-Python: >=3.6
License-File: LICENSE.lic
Dynamic: author
Dynamic: author-email
Dynamic: classifier
Dynamic: license-file
Dynamic: requires-python
Dynamic: summary
